pyswaggerapiwrap/__init__.py
pyswaggerapiwrap/additional_apis.py
pyswaggerapiwrap/api_filter.py
pyswaggerapiwrap/api_route.py
pyswaggerapiwrap/http_client.py
pyswaggerapiwrap/status.py
pyswaggerapiwrap/utils.py
pyswaggerapiwrap-0.1.9.dist-info/LICENSE
pyswaggerapiwrap-0.1.9.dist-info/METADATA
pyswaggerapiwrap-0.1.9.dist-info/WHEEL
pyswaggerapiwrap-0.1.9.dist-info/RECORD
