Metadata-Version: 2.1
Name: pyswaggerapiwrap
Version: 0.1.9
Summary: Python wrapper for api with a swagger
License: MIT
Author: KlajdiBeqiraj
Author-email: k.beqiraj@myw.ai
Requires-Python: >=3.9,<4.0
Classifier: License :: OSI Approved :: MIT License
Classifier: Programming Language :: Python :: 3
Classifier: Programming Language :: Python :: 3.9
Classifier: Programming Language :: Python :: 3.10
Classifier: Programming Language :: Python :: 3.11
Classifier: Programming Language :: Python :: 3.12
Requires-Dist: jupyterlab (>=4.2.4,<5.0.0)
Requires-Dist: pandas (>=2.2.2,<3.0.0)
Requires-Dist: pre-commit (>=3.8.0,<4.0.0)
Requires-Dist: pydantic (>=2.8.2,<3.0.0)
Requires-Dist: pytest (>=8.3.2,<9.0.0)
Requires-Dist: requests (>=2.32.3,<3.0.0)
Requires-Dist: requests-toolbelt (>=1.0.0,<2.0.0)
Requires-Dist: twine (>=5.1.1,<6.0.0)
